portscan.py
beard_portscan-0.1.5.dist-info/LICENSE
beard_portscan-0.1.5.dist-info/METADATA
beard_portscan-0.1.5.dist-info/WHEEL
beard_portscan-0.1.5.dist-info/entry_points.txt
beard_portscan-0.1.5.dist-info/top_level.txt
beard_portscan-0.1.5.dist-info/RECORD
