Metadata-Version: 2.1
Name: beard-portscan
Version: 0.1.5
Summary: Simple port scanning utility at terminal forked from Aperocky/PortScan
Home-page: https://github.com/beardedtek/PortScan
Author: The Bearded Tek
Author-email: kenny@beardedtek.com
License: MIT
Project-URL: Bug Tracker, https://github.com/beardedtek/PortScan/issues
Keywords: port,scanner,multithreading,queue,terminal,utility
Platform: UNKNOWN
Classifier: Environment :: Console
Classifier: License :: OSI Approved :: GNU General Public License v3 (GPLv3)
Classifier: Natural Language :: English
Classifier: Operating System :: MacOS :: MacOS X
Classifier: Operating System :: POSIX
Classifier: Operating System :: Unix
Classifier: Programming Language :: Python :: 3
Classifier: Topic :: Utilities
License-File: LICENSE
